blackfeed/__init__.py
blackfeed/downloader.py
blackfeed/elasticdownloader.py
blackfeed/adapter/__init__.py
blackfeed/adapter/local.py
blackfeed/adapter/s3.py
blackfeed/elastic/__init__.py
blackfeed/elastic/ftp.py
blackfeed/elastic/sftp.py
blackfeed/helper/__init__.py
blackfeed/helper/hasher.py
blackfeed/helper/http_download.py
blackfeed-0.0.19.dist-info/METADATA
blackfeed-0.0.19.dist-info/WHEEL
blackfeed-0.0.19.dist-info/top_level.txt
blackfeed-0.0.19.dist-info/RECORD
