Metadata-Version: 2.1
Name: blackfeed
Version: 0.0.19
Summary: A python package that allows the download of thousands of files concurrently
Home-page: https://github.com/ibra-akv/blackfeed
Author: Ibragim Abubakarov
Author-email: ibragim.ai95@gmail.com
Maintainer: Ibragim Abubakarov
Maintainer-email: ibragim.ai95@gmail.com
License: UNKNOWN
Platform: UNKNOWN
Classifier: Programming Language :: Python :: 3
Classifier: Operating System :: OS Independent
Classifier: Intended Audience :: Developers
Classifier: Topic :: Internet :: WWW/HTTP
Classifier: Topic :: Internet :: File Transfer Protocol (FTP)
Requires-Dist: boto3
Requires-Dist: pysftp
Requires-Dist: requests
